{"_invocation_id": "05095cc5-bf20-4af1-b394-b9c403e0359f", "linked": {"0": {"name": "source.makeopendata.sources.cog_poste", "type": "source", "succ": [24, 36, 37, 23, 40, 41, 42, 48]}, "1": {"name": "source.makeopendata.sources.cog_communes", "type": "source", "succ": [23, 40, 46]}, "2": {"name": "source.makeopendata.sources.cog_arrondissements", "type": "source", "succ": [23, 47]}, "3": {"name": "source.makeopendata.sources.cog_departements", "type": "source", "succ": [36, 37, 23, 49]}, "4": {"name": "source.makeopendata.sources.cog_regions", "type": "source", "succ": [36, 37, 23, 45]}, "5": {"name": "source.makeopendata.sources.dvf_2023", "type": "source", "succ": [43]}, "6": {"name": "source.makeopendata.sources.logement_2020", "type": "source"}, "7": {"name": "source.makeopendata.sources.professionels_sante", "type": "source", "succ": [38, 53]}, "8": {"name": "source.makeopendata.sources.logement_2020_dev", "type": "source", "succ": [17, 19, 20, 21]}, "9": {"name": "source.makeopendata.sources.dvf_2023_dev", "type": "source", "succ": [22]}, "10": {"name": "source.makeopendata.sources.filosofi_commune_2021", "type": "source", "succ": [35, 86, 87]}, "11": {"name": "source.makeopendata.sources.filosofi_iris_2021", "type": "source", "succ": [39, 88, 89]}, "12": {"name": "source.makeopendata.sources.shape_commune_2024", "type": "source", "succ": [23]}, "13": {"name": "source.makeopendata.sources.shape_arrondissement_municipal_2024", "type": "source", "succ": [23]}, "14": {"name": "source.makeopendata.sources.shape_iris_2024", "type": "source", "succ": [26]}, "15": {"name": "source.makeopendata.meta.logement_2020_variables", "type": "source"}, "16": {"name": "model.makeopendata.fake_knn_data", "type": "model", "succ": [44]}, "17": {"name": "model.makeopendata.demographie_renomee", "type": "model", "succ": [25, 27]}, "18": {"name": "seed.makeopendata.logement_2020_valeurs", "type": "seed", "succ": [17, 19, 20, 21, 25, 27, 28, 29, 30, 31, 32, 33]}, "19": {"name": "model.makeopendata.habitat_renomee", "type": "model", "succ": [28, 29]}, "20": {"name": "model.makeopendata.activite_renomee", "type": "model", "succ": [32, 33]}, "21": {"name": "model.makeopendata.mobilite_renomee", "type": "model", "succ": [30, 31]}, "22": {"name": "model.makeopendata.mutations_foncieres", "type": "model", "succ": [34, 54, 55]}, "23": {"name": "model.makeopendata.infos_communes", "type": "model", "succ": [22, 27, 29, 30, 32, 35, 26, 37, 38, 50, 51, 76, 77]}, "24": {"name": "model.makeopendata.postes_communes", "type": "model"}, "25": {"name": "model.makeopendata.demographie_iris", "type": "model", "succ": [58, 59]}, "26": {"name": "model.makeopendata.infos_iris", "type": "model", "succ": [25, 28, 31, 33, 39]}, "27": {"name": "model.makeopendata.demographie_communes", "type": "model", "succ": [56, 57]}, "28": {"name": "model.makeopendata.habitat_iris", "type": "model", "succ": [62, 63]}, "29": {"name": "model.makeopendata.habitat_communes", "type": "model", "succ": [60, 61]}, "30": {"name": "model.makeopendata.mobilite_communes", "type": "model", "succ": [64, 65]}, "31": {"name": "model.makeopendata.mobilite_iris", "type": "model", "succ": [66, 67]}, "32": {"name": "model.makeopendata.activite_communes", "type": "model", "succ": [68, 69]}, "33": {"name": "model.makeopendata.activite_iris", "type": "model", "succ": [70, 71]}, "34": {"name": "model.makeopendata.mutations_foncieres_enrichies", "type": "model", "succ": [72, 73]}, "35": {"name": "model.makeopendata.revenu_commune", "type": "model", "succ": [74, 75]}, "36": {"name": "model.makeopendata.infos_postes", "type": "model", "succ": [52, 78, 79]}, "37": {"name": "model.makeopendata.commune_centroid_poste", "type": "model"}, "38": {"name": "model.makeopendata.professionels_sante_departement", "type": "model", "succ": [80, 81, 82, 83, 84, 85]}, "39": {"name": "analysis.makeopendata.revenu_iris", "type": "analysis"}, "40": {"name": "analysis.makeopendata.multiple_agg_per_cp", "type": "analysis"}, "41": {"name": "analysis.makeopendata.multiple_cp_per_com", "type": "analysis"}, "42": {"name": "analysis.makeopendata.multiple_com_per_cp", "type": "analysis"}, "43": {"name": "test.makeopendata.assert_one_price_mutation", "type": "test"}, "44": {"name": "test.makeopendata.test_knn", "type": "test"}, "45": {"name": "test.makeopendata.assert_one_reg", "type": "test"}, "46": {"name": "test.makeopendata.assert_one_com", "type": "test"}, "47": {"name": "test.makeopendata.assert_one_arr", "type": "test"}, "48": {"name": "test.makeopendata.assert_one_gps_com", "type": "test"}, "49": {"name": "test.makeopendata.assert_one_dep", "type": "test"}, "50": {"name": "test.makeopendata.asset_geo_communes_distinct", "type": "test"}, "51": {"name": "test.makeopendata.assert_geo_communes_number", "type": "test"}, "52": {"name": "test.makeopendata.assert_geo_postaux_distinct", "type": "test"}, "53": {"name": "test.makeopendata.effectif_tout_departement_egal_some_region", "type": "test"}, "54": {"name": "test.makeopendata.unique_mutations_foncieres_id_mutation.5f27073ab2", "type": "test"}, "55": {"name": "test.makeopendata.not_null_mutations_foncieres_id_mutation.7653319336", "type": "test"}, "56": {"name": "test.makeopendata.unique_demographie_communes_code_commune_insee.99a323b9a8", "type": "test"}, "57": {"name": "test.makeopendata.not_null_demographie_communes_code_commune_insee.a06d1c158d", "type": "test"}, "58": {"name": "test.makeopendata.unique_demographie_iris_code_iris.6f4a6d41ff", "type": "test"}, "59": {"name": "test.makeopendata.not_null_demographie_iris_code_iris.5e934d266a", "type": "test"}, "60": {"name": "test.makeopendata.unique_habitat_communes_code_commune_insee.31652939ba", "type": "test"}, "61": {"name": "test.makeopendata.not_null_habitat_communes_code_commune_insee.4bfaea56ce", "type": "test"}, "62": {"name": "test.makeopendata.unique_habitat_iris_code_iris.e938aeede9", "type": "test"}, "63": {"name": "test.makeopendata.not_null_habitat_iris_code_iris.f403285d90", "type": "test"}, "64": {"name": "test.makeopendata.unique_mobilite_communes_code_commune_insee.0bb420935f", "type": "test"}, "65": {"name": "test.makeopendata.not_null_mobilite_communes_code_commune_insee.3ff1215dfa", "type": "test"}, "66": {"name": "test.makeopendata.unique_mobilite_iris_code_iris.1d6c4aa554", "type": "test"}, "67": {"name": "test.makeopendata.not_null_mobilite_iris_code_iris.3dccdfc834", "type": "test"}, "68": {"name": "test.makeopendata.unique_activite_communes_code_commune_insee.a16d20ff24", "type": "test"}, "69": {"name": "test.makeopendata.not_null_activite_communes_code_commune_insee.705d4ded03", "type": "test"}, "70": {"name": "test.makeopendata.unique_activite_iris_code_iris.a827b233ce", "type": "test"}, "71": {"name": "test.makeopendata.not_null_activite_iris_code_iris.d48378cef2", "type": "test"}, "72": {"name": "test.makeopendata.unique_mutations_foncieres_enrichies_id_mutation.eaae35cfca", "type": "test"}, "73": {"name": "test.makeopendata.not_null_mutations_foncieres_enrichies_id_mutation.69469c1753", "type": "test"}, "74": {"name": "test.makeopendata.unique_revenu_commune__code_commune_2024_.89ea270e4d", "type": "test"}, "75": {"name": "test.makeopendata.not_null_revenu_commune__code_commune_2024_.51e2e25aa8", "type": "test"}, "76": {"name": "test.makeopendata.unique_infos_communes_code_commune.9c66e801cd", "type": "test"}, "77": {"name": "test.makeopendata.not_null_infos_communes_code_commune.4e03754490", "type": "test"}, "78": {"name": "test.makeopendata.unique_infos_postes_code_postal.ecffc082fd", "type": "test"}, "79": {"name": "test.makeopendata.not_null_infos_postes_code_postal.95fe263c82", "type": "test"}, "80": {"name": "test.makeopendata.not_null_professionels_sante_departement_region.204f3127e8", "type": "test"}, "81": {"name": "test.makeopendata.not_null_professionels_sante_departement_libelle_region.350a716b1b", "type": "test"}, "82": {"name": "test.makeopendata.unique_professionels_sante_departement_departement.075a531ca0", "type": "test"}, "83": {"name": "test.makeopendata.not_null_professionels_sante_departement_departement.2b0d9839bd", "type": "test"}, "84": {"name": "test.makeopendata.unique_professionels_sante_departement_libelle_departement.ca5b280ea3", "type": "test"}, "85": {"name": "test.makeopendata.not_null_professionels_sante_departement_libelle_departement.3f71960534", "type": "test"}, "86": {"name": "test.makeopendata.source_unique_sources_filosofi_commune_2021__CODGEO_.bef3b826e4", "type": "test"}, "87": {"name": "test.makeopendata.source_not_null_sources_filosofi_commune_2021__CODGEO_.7073b9c75b", "type": "test"}, "88": {"name": "test.makeopendata.source_unique_sources_filosofi_iris_2021__IRIS_.d12e654b6c", "type": "test"}, "89": {"name": "test.makeopendata.source_not_null_sources_filosofi_iris_2021__IRIS_.96aa188bf7", "type": "test"}}}